django_docker_helper/__init__.py
django_docker_helper/apps.py
django_docker_helper/management/docker_services.py
django_docker_helper/management/path.py
django_docker_helper/management/commands/docker_compose.py
django_docker_helper/management/commands/docker_file.py
django_docker_helper-1.0.0.1.dist-info/LICENSE.txt
django_docker_helper-1.0.0.1.dist-info/METADATA
django_docker_helper-1.0.0.1.dist-info/WHEEL
django_docker_helper-1.0.0.1.dist-info/top_level.txt
django_docker_helper-1.0.0.1.dist-info/RECORD
