Metadata-Version: 2.1
Name: django-docker-helper
Version: 1.0.0.1
Summary: A Django package to simplify the creation of Dockerfile and docker-compose.yml files.
Home-page: https://github.com/SakariaNdadi/django-docker-helper
Author: Sakaria Ndadi
Author-email: oipapi.ndadi@gmail.com
License: BSD-3-Clause
Keywords: django docker docker-compose
Classifier: Development Status :: 5 - Production/Stable
Classifier: Environment :: Web Environment
Classifier: Framework :: Django
Classifier: Intended Audience :: Developers
Classifier: Operating System :: OS Independent
Classifier: Programming Language :: Python
Classifier: Programming Language :: Python :: 3
Classifier: Programming Language :: Python :: 3 :: Only
Classifier: Programming Language :: Python :: 3.10
Classifier: Programming Language :: Python :: 3.11
Classifier: Programming Language :: Python :: 3.12
Classifier: Topic :: Software Development :: Libraries :: Python Modules
License-File: LICENSE.txt
